fast_psq/__init__.py
fast_psq/index.py
fast_psq/search.py
fast_psq/tokenizer.py
fast_psq/utils.py
fast_psq/vectorizer.py
fast_psq-0.1.0.dist-info/LICENSE
fast_psq-0.1.0.dist-info/METADATA
fast_psq-0.1.0.dist-info/WHEEL
fast_psq-0.1.0.dist-info/top_level.txt
fast_psq-0.1.0.dist-info/RECORD
